pyocpp_heroyooki/__init__.py
pyocpp_heroyooki/settings.py
pyocpp_heroyooki-0.0.1.dist-info/METADATA
pyocpp_heroyooki-0.0.1.dist-info/WHEEL
pyocpp_heroyooki-0.0.1.dist-info/top_level.txt
pyocpp_heroyooki-0.0.1.dist-info/RECORD
