Metadata-Version: 2.1
Name: pyocpp-heroyooki
Version: 0.0.1
Summary: A small helper with shared components for building ocpp csms.
Author-email: Denis Zyazev <denis.zyazev@gmail.com>
Requires-Python: >=3.10
Requires-Dist: aio-pika ==9.3.0
Requires-Dist: arrow ==1.2.3
Requires-Dist: httpx ==0.25.0
Requires-Dist: loguru ==0.7.2
Requires-Dist: ocpp ==0.19.0
Requires-Dist: pydantic ==2.3.0
